sshclick/__init__.py
sshclick/cmds/__init__.py
sshclick/cmds/cmd_config.py
sshclick/cmds/cmd_group.py
sshclick/cmds/cmd_host.py
sshclick/cmds/config/__init__.py
sshclick/cmds/config/config_del.py
sshclick/cmds/config/config_set.py
sshclick/cmds/group/__init__.py
sshclick/cmds/group/group_create.py
sshclick/cmds/group/group_delete.py
sshclick/cmds/group/group_list.py
sshclick/cmds/group/group_rename.py
sshclick/cmds/group/group_set.py
sshclick/cmds/group/group_show.py
sshclick/cmds/host/__init__.py
sshclick/cmds/host/host_create.py
sshclick/cmds/host/host_delete.py
sshclick/cmds/host/host_install_key.py
sshclick/cmds/host/host_list.py
sshclick/cmds/host/host_rename.py
sshclick/cmds/host/host_set.py
sshclick/cmds/host/host_show.py
sshclick/cmds/host/host_test.py
sshclick/globals.py
sshclick/main.py
sshclick/main_tui.py
sshclick/sshc/__init__.py
sshclick/sshc/host_styles/__init__.py
sshclick/sshc/host_styles/card.py
sshclick/sshc/host_styles/json.py
sshclick/sshc/host_styles/panels.py
sshclick/sshc/host_styles/simple.py
sshclick/sshc/host_styles/table.py
sshclick/sshc/host_styles/table2.py
sshclick/sshc/ssh_config.py
sshclick/sshc/ssh_graph.py
sshclick/sshc/ssh_group.py
sshclick/sshc/ssh_host.py
sshclick/sshc/ssh_parameters.py
sshclick/sshc/sshutils.py
sshclick/version.py
sshclick-0.6.1.dist-info/LICENSE
sshclick-0.6.1.dist-info/METADATA
sshclick-0.6.1.dist-info/WHEEL
sshclick-0.6.1.dist-info/entry_points.txt
sshclick-0.6.1.dist-info/RECORD
