Metadata-Version: 2.1
Name: sshclick
Version: 0.6.1
Summary: SSH Config manager
Home-page: https://github.com/karlot/sshclick
License: MIT
Author: Karlo Tisaj
Author-email: karlot@gmail.com
Requires-Python: >=3.7,<4.0
Classifier: Development Status :: 3 - Alpha
Classifier: Environment :: Console
Classifier: License :: OSI Approved :: MIT License
Classifier: Operating System :: POSIX :: Linux
Classifier: Programming Language :: Python :: 3
Classifier: Programming Language :: Python :: 3.7
Classifier: Programming Language :: Python :: 3.8
Classifier: Programming Language :: Python :: 3.9
Classifier: Programming Language :: Python :: 3.10
Classifier: Programming Language :: Python :: 3.11
Requires-Dist: click (>=8.1,<9.0)
Requires-Dist: rich (>=13.3,<14.0)
Requires-Dist: textual (>=0.26,<0.27)
